graphene_pagination/__init__.py
graphene_pagination/connection.py
graphene_pagination/connection_field.py
graphene_pagination/objects_type.py
graphene_pagination-1.0.1.dist-info/LICENSE
graphene_pagination-1.0.1.dist-info/METADATA
graphene_pagination-1.0.1.dist-info/WHEEL
graphene_pagination-1.0.1.dist-info/top_level.txt
graphene_pagination-1.0.1.dist-info/RECORD
