Metadata-Version: 2.1
Name: graphene-pagination
Version: 1.0.1
Summary: UNKNOWN
Home-page: https://github.com/null-none/graphene-pagination
Author: Dmitry Kalinin
License: UNKNOWN
Platform: UNKNOWN
License-File: LICENSE
Requires-Dist: graphene-django
